dylightful/__init__.py
dylightful/bar_plot.py
dylightful/discretizer.py
dylightful/dylightful.py
dylightful/mdanalysis.py
dylightful/metrics.py
dylightful/msm.py
dylightful/parser.py
dylightful/plot_hmm.py
dylightful/postprocess.py
dylightful/preanalysis.py
dylightful/utilities.py
dylightful-0.3.0.dist-info/LICENSE
dylightful-0.3.0.dist-info/METADATA
dylightful-0.3.0.dist-info/WHEEL
dylightful-0.3.0.dist-info/top_level.txt
dylightful-0.3.0.dist-info/RECORD
