Metadata-Version: 2.1
Name: dylightful
Version: 0.3.0
Summary: Package to uncover hidden interaction patterns in supramolecular complexes
Home-page: https://github.com/MQSchleich/dylightful
Author: Julian M. Kleber
Author-email: julian.m.kleber@gmail.com
License: MIT
License-File: LICENSE
Requires-Dist: pandas
Requires-Dist: scikit-learn
Requires-Dist: hmmlearn
Requires-Dist: deeptime
Requires-Dist: torch
Requires-Dist: torchvision
Requires-Dist: torchaudio
Requires-Dist: matplotlib
Requires-Dist: tqdm
Requires-Dist: MDAnalysis
Requires-Dist: seaborn
Requires-Dist: mdtraj
